AUTHORS.rst
CONTRIBUTING.rst
HISTORY.rst
LICENSE
MANIFEST.in
README.rst
setup.cfg
setup.py
docs/Makefile
docs/authors.rst
docs/conf.py
docs/contributing.rst
docs/history.rst
docs/index.rst
docs/installation.rst
docs/make.bat
docs/readme.rst
docs/usage.rst
faws/__init__.py
faws/api.py
faws/cli.py
faws/core.py
faws.egg-info/PKG-INFO
faws.egg-info/SOURCES.txt
faws.egg-info/dependency_links.txt
faws.egg-info/entry_points.txt
faws.egg-info/not-zip-safe
faws.egg-info/requires.txt
faws.egg-info/top_level.txt
tests/test_faws.py