Metadata-Version: 1.1
Name: faws
Version: 0.1.2
Summary: Fast, functional AWS lib bases on boto3
Home-page: https://github.com/hvnsweeting/faws
Author: Viet Hung Nguyen
Author-email: hvn@familug.org
License: MIT license
Keywords: faws
Platform: UNKNOWN
Classifier: Development Status :: 2 - Pre-Alpha
Classifier: Intended Audience :: Developers
Classifier: License :: OSI Approved :: MIT License
Classifier: Natural Language :: English
Classifier: Programming Language :: Python :: 2
Classifier: Programming Language :: Python :: 2.7
Classifier: Programming Language :: Python :: 3
Classifier: Programming Language :: Python :: 3.4
Classifier: Programming Language :: Python :: 3.5
Classifier: Programming Language :: Python :: 3.6
